clicamap2cal/__init__.py
clicamap2cal/cli.py
clicamap2cal/clicamap/__init__.py
clicamap2cal/clicamap/client.py
clicamap2cal/logging.py
clicamap2cal/py.typed
clicamap2cal/settings.py
clicamap2cal-0.3.0.dist-info/METADATA
clicamap2cal-0.3.0.dist-info/WHEEL
clicamap2cal-0.3.0.dist-info/entry_points.txt
clicamap2cal-0.3.0.dist-info/licenses/LICENSE
clicamap2cal-0.3.0.dist-info/RECORD
