Metadata-Version: 2.4
Name: clicamap2cal
Version: 0.3.0
Summary: Convert your clicamap HTML calendar to an ical ready to import
License-Expression: CECILL-B
License-File: LICENSE
Author: Rémi Ferrand
Author-email: riton.github@gmail.com
Maintainer: Rémi Ferrand
Maintainer-email: riton.github@gmail.com
Requires-Python: >=3.12,<4.0
Classifier: Programming Language :: Python :: 3
Classifier: Programming Language :: Python :: 3.12
Classifier: Programming Language :: Python :: 3.13
Classifier: Programming Language :: Python :: 3.14
Requires-Dist: ics (>=0.7.2,<0.8.0)
Requires-Dist: loguru (>=0.7.3,<0.8.0)
Requires-Dist: lxml (>=5.3.1,<6.0.0)
Requires-Dist: pydantic-settings (>=2.7.1,<3.0.0)
Requires-Dist: pytz (>=2025.1,<2026.0)
Requires-Dist: requests (>=2.32.3,<3.0.0)
Project-URL: Documentation, https://gitlab.com/riton/clicamap-calendar
Project-URL: Homepage, https://gitlab.com/riton/clicamap-calendar
Project-URL: Repository, https://gitlab.com/riton/clicamap-calendar
